floraflow/__init__.py
floraflow/testFinal.py
floraflow/features/__init__.py
floraflow/features/data_builder.py
floraflow/features/segmentation.py
floraflow/models/__init__.py
floraflow/models/campaign.py
floraflow/models/model_wrapper.py
floraflow/models/models.py
floraflow/models/final_test/__init__.py
floraflow/models/final_test/stage1.py
floraflow/models/final_test/stage2.py
floraflow/models/final_test/stage3.py
floraflow/models/final_test/stage4.py
floraflow/visualization/__init__.py
floraflow/visualization/eda.py
floraflow/visualization/graphs.py
floraflow-0.1.3.dist-info/METADATA
floraflow-0.1.3.dist-info/WHEEL
floraflow-0.1.3.dist-info/top_level.txt
floraflow-0.1.3.dist-info/RECORD
